pyfixture/__init__.py
pyfixture/decorators.py
pyfixture/exceptions.py
pyfixture/fixturedefs.py
pyfixture/scopes.py
tests/__init__.py
tests/pyfixture/__init__.py
tests/pyfixture/test_decorators.py
tests/pyfixture/test_fixturedefs.py
tests/pyfixture/test_scopes.py
pyfixture-0.7.dist-info/LICENSE
pyfixture-0.7.dist-info/METADATA
pyfixture-0.7.dist-info/WHEEL
pyfixture-0.7.dist-info/top_level.txt
pyfixture-0.7.dist-info/RECORD
