Metadata-Version: 2.1
Name: pyfixture
Version: 0.7
Summary: pytest style fixtures outside pytest
Author: Ivan Georgiev
License: GNU-3
Project-URL: Source, https://github.com/ivangeorgiev/py-fixture
Project-URL: Documentation, http://py-fixture.readthedocs.io/
Keywords: fixture
Classifier: Programming Language :: Python :: 3
Requires-Python: >=3.7
License-File: LICENSE
